unimog/__init__.py
unimog/action.py
unimog/context.py
unimog/organizer.py
unimog-0.3.0.dist-info/LICENSE
unimog-0.3.0.dist-info/METADATA
unimog-0.3.0.dist-info/WHEEL
unimog-0.3.0.dist-info/RECORD
