Metadata-Version: 2.1
Name: unimog
Version: 0.3.0
Summary: Elegant service objects for Python.
Home-page: https://github.com/eliias/unimog
License: MIT
Keywords: service object,organize,action,business logic
Author: Hannes Moser
Author-email: box@hannesmoser.at
Requires-Python: >=3.11,<4.0
Classifier: Intended Audience :: Developers
Classifier: Intended Audience :: Information Technology
Classifier: License :: OSI Approved :: MIT License
Classifier: Programming Language :: Python :: 3
Classifier: Programming Language :: Python :: 3.11
Classifier: Programming Language :: Python :: 3.12
Classifier: Topic :: Software Development
Classifier: Topic :: Software Development :: Libraries
Classifier: Topic :: Software Development :: Libraries :: Python Modules
Classifier: Typing :: Typed
Project-URL: Repository, https://github.com/eliias/unimog
